aiontai/__init__.py
aiontai/api.py
aiontai/client.py
aiontai/converter.py
aiontai/models.py
aiontai/modules.py
aiontai-1.0.12.dist-info/LICENSE
aiontai-1.0.12.dist-info/WHEEL
aiontai-1.0.12.dist-info/METADATA
aiontai-1.0.12.dist-info/RECORD
