Metadata-Version: 2.1
Name: aiontai
Version: 1.0.12
Summary: Async wrapper for nhentai API
Home-page: https://github.com/LEv145/aiontai
License: MIT
Author: LEv145
Requires-Python: >=3.8,<4.0
Classifier: License :: OSI Approved :: MIT License
Classifier: Programming Language :: Python :: 3
Classifier: Programming Language :: Python :: 3.10
Classifier: Programming Language :: Python :: 3.8
Classifier: Programming Language :: Python :: 3.9
Requires-Dist: aiohttp (>=3.8.1,<4.0.0)
Requires-Dist: darglint (>=1.8.1,<2.0.0)
Requires-Dist: dataclasses-json (>=0.5.6,<0.6.0)
Requires-Dist: injector (>=0.19.0,<0.20.0)
Project-URL: Documentation, https://aiontai.readthedocs.io/en/latest/
